setup.py
drf_fsm_transitions/__init__.py
drf_fsm_transitions/viewset_mixins.py
drf_fsm_transitions.egg-info/PKG-INFO
drf_fsm_transitions.egg-info/SOURCES.txt
drf_fsm_transitions.egg-info/dependency_links.txt
drf_fsm_transitions.egg-info/requires.txt
drf_fsm_transitions.egg-info/top_level.txt