Metadata-Version: 1.0
Name: drf-fsm-transitions
Version: 0.2.0
Summary: Automatically hook your Django-FSM transitions up to Django REST Framework
Home-page: https://github.com/hzy/drf-fsm-transitions
Author: Jacob Haslehurst
Author-email: jacob@haslehurst.net
License: UNKNOWN
Platform: UNKNOWN
